llmbo/__init__.py
llmbo/batch_inferer.py
llmbo/models.py
llmbo/registry.py
llmbo/structured_batch_inferer.py
llmbo/adapters/__init__.py
llmbo/adapters/anthropic.py
llmbo/adapters/base.py
llmbo/adapters/mistral.py
llmbo/adapters/mistral_function_calling.py
llmbo_bedrock-0.2.2.dist-info/METADATA
llmbo_bedrock-0.2.2.dist-info/WHEEL
llmbo_bedrock-0.2.2.dist-info/licenses/LICENSE
llmbo_bedrock-0.2.2.dist-info/RECORD
