Metadata-Version: 2.4
Name: llmbo-bedrock
Version: 0.2.2
Summary: Large Language Model Batch Operations
Project-URL: Homepage, https://co-cddo.github.io/gds-idea-llmbo/
Project-URL: Documentation, https://co-cddo.github.io/gds-idea-llmbo/api/
Project-URL: Repository, https://github.com/co-cddo/gds-idea-llmbo.git
Project-URL: Issues, https://github.com/co-cddo/gds-idea-llmbo/issues
Author-email: David Gillespie <david.gillespie@digital.cabinet-office.gov.uk>
License-File: LICENSE
Requires-Python: >=3.10
Requires-Dist: boto3<2.0,>=1.3
Requires-Dist: pydantic>=2.10
Requires-Dist: python-dotenv>=1.0.1
